{"uniqueId": 46240585695288390597081388870, "activities": [{"name": "anr", "time": -7401.075960048555, "duration": 26976}, {"name": "singleTap", "time": -229.42175469240522, "duration": 27730}, {"name": "singleTap", "time": 1654968031.9592965, "duration": 17427}, {"name": "crash", "time": -1443.504522297914, "duration": 15579}, {"name": "singleTap", "time": 1654968031.9593058, "duration": 13850}, {"name": "singleTap", "time": 1654968031.95931, "duration": 25322}, {"name": "crash", "time": -9406.63771483034, "duration": 16833}, {"name": "invalid", "time": 1654968031.9593174, "duration": 11064}, {"name": "doubleTap", "time": 1654968031.9593215, "duration": 23884}, {"name": "anr", "time": -7510.805212458958, "duration": 13367}]}