{"uniqueId": 793002318972437843874120482624, "activities": [{"name": "doubleTap", "time": 1654968032.1385217, "duration": 10864}, {"name": "anr", "time": 1654968032.1385272, "duration": 11906}, {"name": "singleTap", "time": 1654968032.138532, "duration": 27355}, {"name": "invalid", "time": 1654968032.1385357, "duration": 16971}, {"name": "crash", "time": 1654968032.1385398, "duration": 26575}, {"name": "doubleTap", "time": 1654968032.1385438, "duration": 12052}, {"name": "crash", "time": 1654968032.1385477, "duration": 21898}, {"name": "anr", "time": 1654968032.1385517, "duration": 15940}, {"name": "doubleTap", "time": 1654968032.1385553, "duration": 1013}, {"name": "anr", "time": 1654968032.13856, "duration": 1647}]}