{"uniqueId": 102082163330875053951587964069, "activities": [{"name": "invalid", "time": 1654968032.2147713, "duration": 3165}, {"name": "anr", "time": 1654968032.2147768, "duration": 1535}, {"name": "singleTap", "time": -6008.259982746156, "duration": 2977}, {"name": "anr", "time": 1654968032.2147856, "duration": 12550}, {"name": "anr", "time": 1654968032.2147899, "duration": 4295}, {"name": "crash", "time": 1654968032.2147944, "duration": 25974}, {"name": "invalid", "time": 1654968032.2147985, "duration": 2409}, {"name": "crash", "time": 1654968032.2148023, "duration": 11193}, {"name": "anr", "time": 1654968032.214806, "duration": 16106}, {"name": "anr", "time": 1654968032.2148101, "duration": 18612}]}