{"uniqueId": 339130323729988967827048135669, "activities": [{"name": "invalid", "time": -2547.561807474264, "duration": 895}, {"name": "doubleTap", "time": -2961.4083213258086, "duration": 20313}, {"name": "crash", "time": 1654968031.8619633, "duration": 26438}, {"name": "anr", "time": 1654968031.8619719, "duration": 4310}, {"name": "anr", "time": 1654968031.861976, "duration": 13865}, {"name": "crash", "time": 1654968031.8619795, "duration": 20182}, {"name": "doubleTap", "time": 1654968031.8619833, "duration": 12500}, {"name": "crash", "time": 1654968031.861987, "duration": 23412}, {"name": "singleTap", "time": 1654968031.861991, "duration": 13725}, {"name": "anr", "time": -2900.297232300099, "duration": 19572}]}