{"uniqueId": 202462116727167789720255638359, "activities": [{"name": "doubleTap", "time": 1654968031.9696808, "duration": 17251}, {"name": "doubleTap", "time": 1654968031.9696872, "duration": 15814}, {"name": "anr", "time": 1654968031.969692, "duration": 29167}, {"name": "doubleTap", "time": 1654968031.969696, "duration": 28519}, {"name": "doubleTap", "time": 1654968031.9696999, "duration": 5942}, {"name": "crash", "time": 1654968031.9697042, "duration": 17048}, {"name": "singleTap", "time": 1654968031.9697082, "duration": 29056}, {"name": "singleTap", "time": 1654968031.9697125, "duration": 3776}, {"name": "singleTap", "time": -2998.018383811949, "duration": 11742}, {"name": "singleTap", "time": -2344.521192829143, "duration": 9084}]}