{"unique_id": 3257204701, "activities": [{"name": "anr", "time": 1654980554, "duration": 848}, {"name": "invalid", "time": 1654980554, "duration": 26341}, {"name": "doubleTap", "time": -6760.175693180629, "duration": 15657}, {"name": "crash", "time": 1654980554, "duration": 7181}, {"name": "crash", "time": 1654980554, "duration": 6143}, {"name": "crash", "time": 1654980554, "duration": 25763}, {"name": "anr", "time": 1654980554, "duration": 10560}, {"name": "crash", "time": 1654980554, "duration": 20187}, {"name": "invalid", "time": 1654980554, "duration": 29235}, {"name": "anr", "time": -7514.921162031574, "duration": 6802}]}