{"uniqueId": 1088293690157416368637824355911, "activities": [{"name": "invalid", "time": 1654968031.7315617, "duration": 14337}, {"name": "anr", "time": 1654968031.7315702, "duration": 15785}, {"name": "singleTap", "time": 1654968031.7315774, "duration": 19381}, {"name": "doubleTap", "time": 1654968031.7315838, "duration": 25066}, {"name": "singleTap", "time": -9028.74422481162, "duration": 9631}, {"name": "singleTap", "time": 1654968031.7316027, "duration": 1712}, {"name": "doubleTap", "time": 1654968031.7316067, "duration": 10880}, {"name": "crash", "time": -8829.705283749789, "duration": 3162}, {"name": "anr", "time": 1654968031.7316175, "duration": 21847}, {"name": "crash", "time": 1654968031.7316256, "duration": 27573}]}