{"uniqueId": 667600387367493861726434205334, "activities": [{"name": "anr", "time": 1654968031.980764, "duration": 8854}, {"name": "anr", "time": 1654968031.9807696, "duration": 24203}, {"name": "crash", "time": 1654968031.9807737, "duration": 13700}, {"name": "crash", "time": 1654968031.980778, "duration": 12599}, {"name": "crash", "time": -8372.083801078905, "duration": 5566}, {"name": "singleTap", "time": 1654968031.9807873, "duration": 10119}, {"name": "singleTap", "time": 1654968031.9807913, "duration": 24588}, {"name": "doubleTap", "time": 1654968031.9807956, "duration": 4382}, {"name": "crash", "time": 1654968031.9808, "duration": 18943}, {"name": "crash", "time": 1654968031.9808044, "duration": 12972}]}