{"uniqueId": 191787264498431255307062604223, "activities": [{"name": "singleTap", "time": 1654968032.1218896, "duration": 23422}, {"name": "doubleTap", "time": 1654968032.1218953, "duration": 6590}, {"name": "singleTap", "time": 1654968032.1218998, "duration": 606}, {"name": "anr", "time": 1654968032.1219041, "duration": 22029}, {"name": "singleTap", "time": 1654968032.121908, "duration": 23173}, {"name": "invalid", "time": 1654968032.121912, "duration": 16127}, {"name": "crash", "time": 1654968032.12193, "duration": 24039}, {"name": "crash", "time": 1654968032.121934, "duration": 9390}, {"name": "singleTap", "time": -9884.912000406383, "duration": 8954}, {"name": "anr", "time": 1654968032.1219416, "duration": 5013}]}