{"uniqueId": 922405454096696666839575813247, "activities": [{"name": "crash", "time": 1654968031.724914, "duration": 27867}, {"name": "invalid", "time": 1654968031.724924, "duration": 9687}, {"name": "doubleTap", "time": 1654968031.7249324, "duration": 19845}, {"name": "anr", "time": -9755.805602176757, "duration": 2747}, {"name": "singleTap", "time": 1654968031.7249503, "duration": 3570}, {"name": "crash", "time": 1654968031.7249591, "duration": 22859}, {"name": "anr", "time": 1654968031.7249682, "duration": 16860}, {"name": "invalid", "time": 1654968031.7249763, "duration": 27055}, {"name": "singleTap", "time": 1654968031.7249851, "duration": 7175}, {"name": "anr", "time": -5403.245646492988, "duration": 25659}]}