{"uniqueId": 1242472155145840090816089322602, "activities": [{"name": "doubleTap", "time": 1654968032.2741742, "duration": 1286}, {"name": "anr", "time": 1654968032.2741802, "duration": 16807}, {"name": "crash", "time": 1654968032.2741845, "duration": 12671}, {"name": "anr", "time": 1654968032.2741885, "duration": 3483}, {"name": "crash", "time": 1654968032.2741923, "duration": 6861}, {"name": "doubleTap", "time": 1654968032.274197, "duration": 9807}, {"name": "invalid", "time": 1654968032.2742012, "duration": 26846}, {"name": "singleTap", "time": 1654968032.2742052, "duration": 20772}, {"name": "singleTap", "time": 1654968032.274209, "duration": 16977}, {"name": "anr", "time": 1654968032.274213, "duration": 9732}]}