{"uniqueId": 107253726395051994284910325614, "activities": [{"name": "doubleTap", "time": 1654968032.0683281, "duration": 9490}, {"name": "crash", "time": 1654968032.0683343, "duration": 27028}, {"name": "anr", "time": 1654968032.0683389, "duration": 19170}, {"name": "doubleTap", "time": -9179.81593100365, "duration": 23843}, {"name": "singleTap", "time": 1654968032.0683482, "duration": 8539}, {"name": "invalid", "time": 1654968032.0683527, "duration": 17531}, {"name": "anr", "time": -8859.410111915131, "duration": 20673}, {"name": "crash", "time": 1654968032.0683613, "duration": 23121}, {"name": "anr", "time": 1654968032.0683653, "duration": 6384}, {"name": "doubleTap", "time": 1654968032.0683699, "duration": 29590}]}