{"uniqueId": 428459941709006926854384936563, "activities": [{"name": "singleTap", "time": 1654968032.311799, "duration": 1347}, {"name": "anr", "time": 1654968032.3118048, "duration": 21683}, {"name": "invalid", "time": -8051.998090019815, "duration": 17142}, {"name": "invalid", "time": 1654968032.3118134, "duration": 9562}, {"name": "anr", "time": 1654968032.3118174, "duration": 9588}, {"name": "invalid", "time": 1654968032.3118215, "duration": 10373}, {"name": "crash", "time": 1654968032.3118255, "duration": 15939}, {"name": "crash", "time": 1654968032.311829, "duration": 21784}, {"name": "anr", "time": 1654968032.311833, "duration": 21130}, {"name": "singleTap", "time": 1654968032.3118372, "duration": 10080}]}