{"uniqueId": 784651897957765774335775993579, "activities": [{"name": "singleTap", "time": 1654968032.02321, "duration": 20119}, {"name": "crash", "time": 1654968032.0232148, "duration": 13642}, {"name": "anr", "time": -5691.421213884848, "duration": 5881}, {"name": "singleTap", "time": 1654968032.0232234, "duration": 12436}, {"name": "singleTap", "time": 1654968032.0232272, "duration": 13291}, {"name": "invalid", "time": 1654968032.023231, "duration": 10659}, {"name": "anr", "time": 1654968032.0232346, "duration": 6301}, {"name": "doubleTap", "time": 1654968032.0232384, "duration": 28609}, {"name": "crash", "time": -5018.272353149432, "duration": 15174}, {"name": "doubleTap", "time": -7820.587154031722, "duration": 7870}]}