{"uniqueId": 985580138279096283102742845917, "activities": [{"name": "anr", "time": 1654968032.3278227, "duration": 10160}, {"name": "crash", "time": 1654968032.3278282, "duration": 19674}, {"name": "doubleTap", "time": 1654968032.3278325, "duration": 1822}, {"name": "anr", "time": 1654968032.327837, "duration": 143}, {"name": "anr", "time": 1654968032.327841, "duration": 1896}, {"name": "anr", "time": 1654968032.3278453, "duration": 22748}, {"name": "anr", "time": 1654968032.3278494, "duration": 21869}, {"name": "invalid", "time": 1654968032.327854, "duration": 29384}, {"name": "doubleTap", "time": 1654968032.327858, "duration": 2949}, {"name": "invalid", "time": 1654968032.327862, "duration": 3662}]}