{"uniqueId": 38752597464022669032218046225, "activities": [{"name": "crash", "time": 1654968032.2997444, "duration": 5655}, {"name": "doubleTap", "time": 1654968032.2997677, "duration": 26826}, {"name": "crash", "time": 1654968032.2997744, "duration": 25458}, {"name": "anr", "time": 1654968032.2997801, "duration": 27322}, {"name": "invalid", "time": -74.53811333338865, "duration": 7301}, {"name": "anr", "time": 1654968032.2997942, "duration": 21217}, {"name": "singleTap", "time": 1654968032.2998004, "duration": 10377}, {"name": "crash", "time": 1654968032.299806, "duration": 4841}, {"name": "invalid", "time": -4236.184746291374, "duration": 26964}, {"name": "crash", "time": 1654968032.299818, "duration": 5009}]}