{"uniqueId": 388790815756241947419987931485, "activities": [{"name": "anr", "time": 1654968032.0872383, "duration": 5186}, {"name": "singleTap", "time": 1654968032.0872438, "duration": 1796}, {"name": "invalid", "time": -1478.4511204116873, "duration": 4725}, {"name": "anr", "time": 1654968032.087253, "duration": 11761}, {"name": "invalid", "time": -1570.2596129001709, "duration": 26810}, {"name": "doubleTap", "time": -4559.572590065931, "duration": 18924}, {"name": "doubleTap", "time": -7799.957789582984, "duration": 12134}, {"name": "singleTap", "time": 1654968032.0872705, "duration": 24937}, {"name": "singleTap", "time": -1567.3699367465513, "duration": 11156}, {"name": "anr", "time": 1654968032.0872786, "duration": 3546}]}