{"uniqueId": 179625128953185488270735363344, "activities": [{"name": "anr", "time": 1654968032.2502306, "duration": 5761}, {"name": "singleTap", "time": 1654968032.2502363, "duration": 18239}, {"name": "singleTap", "time": 1654968032.2502406, "duration": 9059}, {"name": "doubleTap", "time": 1654968032.2502446, "duration": 10686}, {"name": "anr", "time": -775.2410514902141, "duration": 21884}, {"name": "crash", "time": 1654968032.2502532, "duration": 28764}, {"name": "anr", "time": 1654968032.2502573, "duration": 16479}, {"name": "invalid", "time": 1654968032.250261, "duration": 23342}, {"name": "anr", "time": 1654968032.250265, "duration": 21051}, {"name": "doubleTap", "time": 1654968032.250269, "duration": 21578}]}