{"uniqueId": 524644620655348634977609043755, "activities": [{"name": "invalid", "time": -139.44781603834804, "duration": 29448}, {"name": "invalid", "time": 1654968032.0238366, "duration": 18374}, {"name": "anr", "time": 1654968032.0238411, "duration": 4426}, {"name": "singleTap", "time": 1654968032.0238452, "duration": 18609}, {"name": "doubleTap", "time": 1654968032.0238492, "duration": 26859}, {"name": "crash", "time": -7569.648765147641, "duration": 10539}, {"name": "invalid", "time": -7881.141020746813, "duration": 20828}, {"name": "anr", "time": -6037.26048195704, "duration": 13472}, {"name": "invalid", "time": 1654968032.0238657, "duration": 23400}, {"name": "singleTap", "time": 1654968032.0238702, "duration": 8715}]}